{"id":"OH9K","dependencies":[{"name":"C:\\Users\\Lars\\Desktop\\Portfolio\\Website\\package.json","includedInParent":true,"mtime":1540231080595}],"generated":{"js":"module.exports=\"7943931aa6e794f73039ea5c5430a3f8.svg\";","map":{"mappings":[{"source":"0","name":"module","original":{"line":1,"column":0},"generated":{"line":1,"column":0}},{"source":"0","name":"exports","original":{"line":1,"column":7},"generated":{"line":1,"column":7}},{"source":"0","original":{"line":1,"column":17},"generated":{"line":1,"column":15}}],"sources":{},"lineCount":null}},"hash":"8b42ace5e14efe943d98554bcb0edb21","cacheData":{"env":{}}}